{
    "experiences": [
        {
            "title": "IT Freelancer & Independent Learner",
            "subtitle": "Self-Employed",
            "workType": "Freelance & Personal Projects",
            "workDescription": [
                "Developed web-based applications and academic projects using modern programming technologies.",
                "Designed user interfaces and improved user experiences through personal and collaborative projects.",
                "Continuously explored new technologies and frameworks to enhance software development skills."
            ],
            "dateText": "2023 – Present"
        },
        {
            "title": "Workshop Participant",
            "subtitle": "Technology & Software Development Events",
            "workType": "Training & Certification",
            "workDescription": [
                "Participated in workshops focused on web development, programming, and software engineering.",
                "Learned industry best practices in project development, version control, and teamwork.",
                "Applied acquired knowledge in academic and personal projects."
            ],
            "dateText": "2023 – Present"
        },
        {
            "title": "Team Project Developer",
            "subtitle": "Universitas Singaperbangsa Karawang",
            "workType": "Academic Projects",
            "workDescription": [
                "Collaborated with team members to design and develop software solutions for academic assignments.",
                "Contributed to system analysis, UI/UX design, coding, testing, and project documentation.",
                "Strengthened communication, problem-solving, and teamwork skills through project-based learning."
            ],
            "dateText": "2023 – Present"
        }
    ]
}